[
    {
        "Datum": "2025-03-17",
        "Players": 62014
    },
    {
        "Datum": "2025-03-18",
        "Players": 70653
    },
    {
        "Datum": "2025-03-19",
        "Players": 63286
    },
    {
        "Datum": "2025-03-20",
        "Players": 65467
    },
    {
        "Datum": "2025-03-21",
        "Players": 73210
    },
    {
        "Datum": "2025-03-22",
        "Players": 71734
    },
    {
        "Datum": "2025-03-23",
        "Players": 68976
    },
    {
        "Datum": "2025-03-24",
        "Players": 70021
    },
    {
        "Datum": "2025-03-25",
        "Players": 72424
    },
    {
        "Datum": "2025-03-26",
        "Players": 70726
    },
    {
        "Datum": "2025-03-27",
        "Players": 71171
    },
    {
        "Datum": "2025-03-28",
        "Players": 71997
    },
    {
        "Datum": "2025-03-29",
        "Players": 71590
    },
    {
        "Datum": "2025-03-30",
        "Players": 69652
    },
    {
        "Datum": "2025-03-31",
        "Players": 72037
    },
    {
        "Datum": "2025-04-01",
        "Players": 70897
    },
    {
        "Datum": "2025-04-02",
        "Players": 73212
    },
    {
        "Datum": "2025-04-03",
        "Players": 73821
    },
    {
        "Datum": "2025-04-04",
        "Players": 74737
    },
    {
        "Datum": "2025-04-05",
        "Players": 76518
    },
    {
        "Datum": "2025-04-06",
        "Players": 73219
    },
    {
        "Datum": "2025-04-07",
        "Players": 73332
    },
    {
        "Datum": "2025-04-08",
        "Players": 73670
    },
    {
        "Datum": "2025-04-09",
        "Players": 71627
    },
    {
        "Datum": "2025-04-10",
        "Players": 74210
    },
    {
        "Datum": "2025-04-11",
        "Players": 78048
    },
    {
        "Datum": "2025-04-12",
        "Players": 76906
    },
    {
        "Datum": "2025-04-13",
        "Players": 72490
    },
    {
        "Datum": "2025-04-14",
        "Players": 71488
    },
    {
        "Datum": "2025-04-15",
        "Players": 66703
    },
    {
        "Datum" : "2025-04-16",
        "Players": 66709
    },
    {
        "Datum": "2025-04-17",
        "Players": 67622
    },
    {
        "Datum": "2025-04-18",
        "Players": 65863
    }
]